pcy_algo.py
pcy_algo-0.0.2.dist-info/LICENSE
pcy_algo-0.0.2.dist-info/METADATA
pcy_algo-0.0.2.dist-info/WHEEL
pcy_algo-0.0.2.dist-info/top_level.txt
pcy_algo-0.0.2.dist-info/RECORD
