Metadata-Version: 2.1
Name: pcy-algo
Version: 0.0.2
Summary: PCY implementation in association rule mining
Home-page: UNKNOWN
Author: Murali B
License: UNKNOWN
Keywords: association rule mining,apriori algorithm,data mining
Platform: UNKNOWN
Classifier: Programming Language :: Python :: 3
Classifier: License :: OSI Approved :: MIT License
Classifier: Operating System :: OS Independent
Requires-Python: >=3.6
License-File: LICENSE
Requires-Dist: pandas
